<?xml version="1.0" encoding="UTF-8"?>
<!DOCTYPE suite SYSTEM "http://testng.org/testng-1.0.dtd">
<suite name="All Test Suite">
    <listeners>
        <listener class-name="Test_Listners"/>
    </listeners>
    <test verbose="2" preserve-order="true" name="C:/Users/Shanmugasundharam/Git/Selenium_Hybrid_Framework/Selenium/src/main/java/Execution_Engine/Driver_Script.java">
        <classes><class name="Execution_Engine.Driver_Script">
            <methods>
                <include name="Initalization"/>
                <include name="Initalization2"/>

            </methods>
        </class>
        </classes>
    </test>
</suite>